.gitignore
MANIFEST.in
README.txt
setup.py
collective/__init__.py
collective.anotherdynamicgroupsplugin.egg-info/PKG-INFO
collective.anotherdynamicgroupsplugin.egg-info/SOURCES.txt
collective.anotherdynamicgroupsplugin.egg-info/dependency_links.txt
collective.anotherdynamicgroupsplugin.egg-info/entry_points.txt
collective.anotherdynamicgroupsplugin.egg-info/namespace_packages.txt
collective.anotherdynamicgroupsplugin.egg-info/not-zip-safe
collective.anotherdynamicgroupsplugin.egg-info/requires.txt
collective.anotherdynamicgroupsplugin.egg-info/top_level.txt
collective/anotherdynamicgroupsplugin/__init__.py
collective/anotherdynamicgroupsplugin/config.py
collective/anotherdynamicgroupsplugin/configure.zcml
collective/anotherdynamicgroupsplugin/groupdefinition.py
collective/anotherdynamicgroupsplugin/interfaces.py
collective/anotherdynamicgroupsplugin/monkey.zcml
collective/anotherdynamicgroupsplugin/plugin.py
collective/anotherdynamicgroupsplugin/profiles.zcml
collective/anotherdynamicgroupsplugin/setuphandlers.py
collective/anotherdynamicgroupsplugin/testing.py
collective/anotherdynamicgroupsplugin/util.py
collective/anotherdynamicgroupsplugin/profiles/default/collective.anotherdynamicgroupsplugin_various.txt
collective/anotherdynamicgroupsplugin/profiles/default/metadata.xml
collective/anotherdynamicgroupsplugin/tests/__init__.py
collective/anotherdynamicgroupsplugin/tests/test_doctests.py
collective/anotherdynamicgroupsplugin/tests/test_plone.py
docs/HISTORY.txt