Metadata-Version: 1.1
Name: collective.anotherdynamicgroupsplugin
Version: 1.0.0
Summary: Another way to define dynamic user groups in Plone.
Home-page: http://github.com/collective/collective.anotherdynamicgroupsplugin
Author: Rafael Oliveira
Author-email: rafaelbco@gmail.com
License: GPL version 2
Keywords: plone pas groups
Platform: UNKNOWN
Classifier: Framework :: Plone
Classifier: Framework :: Plone :: 4.3
Classifier: Programming Language :: Python
Classifier: Programming Language :: Python :: 2.7
Classifier: Topic :: Software Development :: Libraries :: Python Modules
